mkarchi/__init__.py
mkarchi/__main__.py
mkarchi/cli.py
mkarchi/data.py
mkarchi/error.py
mkarchi/ignore.py
mkarchi-0.1.7.dist-info/licenses/LICENSE
mkarchi-0.1.7.dist-info/METADATA
mkarchi-0.1.7.dist-info/WHEEL
mkarchi-0.1.7.dist-info/entry_points.txt
mkarchi-0.1.7.dist-info/top_level.txt
mkarchi-0.1.7.dist-info/RECORD
