Metadata-Version: 2.4
Name: mkarchi
Version: 0.1.7
Summary: Create directory and file architecture from a tree structure text file
Author: Soufyan Rachdi
License-Expression: MIT
Keywords: cli,architecture,filesystem,tree
Classifier: Programming Language :: Python :: 3
Classifier: Operating System :: OS Independent
Requires-Python: >=3.7
License-File: LICENSE
Dynamic: license-file
